blind_watermark/__init__.py
blind_watermark/att.py
blind_watermark/blind_watermark.py
blind_watermark/bwm_core.py
blind_watermark/cli_tools.py
blind_watermark/pool.py
blind_watermark/recover.py
blind_watermark/version.py
blind_watermark-0.4.4.dist-info/LICENSE
blind_watermark-0.4.4.dist-info/METADATA
blind_watermark-0.4.4.dist-info/WHEEL
blind_watermark-0.4.4.dist-info/entry_points.txt
blind_watermark-0.4.4.dist-info/top_level.txt
blind_watermark-0.4.4.dist-info/RECORD
