Metadata-Version: 2.1
Name: blind-watermark
Version: 0.4.4
Summary: Blind Watermark in Python
Home-page: https://github.com/guofei9987/blind_watermark
Author: Guo Fei
Author-email: guofei9987@foxmail.com
License: MIT
Platform: linux
Platform: windows
Platform: macos
Requires-Python: >=3.5
Requires-Dist: numpy
Requires-Dist: opencv-python
Requires-Dist: PyWavelets
